setup.py
horse_nonsense/__init__.py
horse_nonsense/flashy.py
horse_nonsense/gifs.py
horse_nonsense/hodor.py
horse_nonsense.egg-info/PKG-INFO
horse_nonsense.egg-info/SOURCES.txt
horse_nonsense.egg-info/dependency_links.txt
horse_nonsense.egg-info/requires.txt
horse_nonsense.egg-info/top_level.txt